GML_KIN/__init__.py
GML_KIN-0.0.2.dist-info/LICENSE
GML_KIN-0.0.2.dist-info/METADATA
GML_KIN-0.0.2.dist-info/WHEEL
GML_KIN-0.0.2.dist-info/top_level.txt
GML_KIN-0.0.2.dist-info/RECORD
