Metadata-Version: 2.1
Name: GML-KIN
Version: 0.0.2
Summary: KIN (K Immediate Neighbors) is a machine learning algorithm inspired by KNN (K Nearest Neighbors) which has been adjusted to graph-structured data.
Home-page: https://github.com/PinaxX/KIN
Author: Pedram Dadkhah
Author-email: Pedram.Dadkhah1374@gmail.com
License: UNKNOWN
Platform: UNKNOWN
Classifier: Programming Language :: Python :: 3
Classifier: License :: OSI Approved :: MIT License
Classifier: Operating System :: OS Independent
Requires-Python: >=3.6
